pycustomrand/__init__.py
pycustomrand/custom_round.py
pycustomrand/diagnostics.py
pycustomrand/random_generator.py
pycustomrand-0.0.2.dist-info/licenses/LICENSE
pycustomrand-0.0.2.dist-info/METADATA
pycustomrand-0.0.2.dist-info/WHEEL
pycustomrand-0.0.2.dist-info/top_level.txt
pycustomrand-0.0.2.dist-info/RECORD
