Metadata-Version: 2.4
Name: pycustomrand
Version: 0.0.2
Summary: Библиотека для генерации псевдослучайных чисел на основе времени
Author-email: Ivan <vanyalebedev45@gmail.com>
Project-URL: Homepage, https://github.com/n1xsi/PyCustomRand
Project-URL: Bug Tracker, https://github.com/n1xsi/PyCustomRand/issues
Classifier: Programming Language :: Python :: 3
Classifier: License :: OSI Approved :: MIT License
Classifier: Operating System :: OS Independent
Requires-Python: >=3.8
License-File: LICENSE
Dynamic: license-file
